business_intelligence/__init__.py
business_intelligence/customer_health.py
business_intelligence/elasticity.py
business_intelligence/statatict.py
business_intelligence-0.20.dist-info/licenses/LICENSE
business_intelligence-0.20.dist-info/METADATA
business_intelligence-0.20.dist-info/WHEEL
business_intelligence-0.20.dist-info/top_level.txt
business_intelligence-0.20.dist-info/RECORD
