Metadata-Version: 2.4
Name: business_intelligence
Version: 0.20
Summary: Tools for business intelligence
Author-email: Alejandro Yegros Schmidt <alejandro_aug@hotmail.com>
License: Copyright (c) 2018 The Python Packaging Authority
Classifier: Programming Language :: Python :: 3
Classifier: Operating System :: OS Independent
Requires-Python: >=3.8
License-File: LICENSE
Requires-Dist: numpy>=2.2.2
Requires-Dist: pandas>=2.2.3
Dynamic: license-file
